cfu_count/__init__.py
cfu_count/culture.py
cfu_count/main.py
cfu_count/poisson.py
cfu_count-0.0.0.dist-info/entry_points.txt
cfu_count-0.0.0.dist-info/LICENSE.txt
cfu_count-0.0.0.dist-info/WHEEL
cfu_count-0.0.0.dist-info/METADATA
cfu_count-0.0.0.dist-info/RECORD
