Metadata-Version: 2.1
Name: cfu_count
Version: 0.0.0
Summary: Infer the cell density of a culture from the number of colonies observed in 
Author-email: Kale Kundert <kale@thekunderts.net>
Requires-Python: ~=3.10
Classifier: Programming Language :: Python :: 3.10
Requires-Dist: numpy
Requires-Dist: scipy
Requires-Dist: pandas
Requires-Dist: matplotlib
Requires-Dist: uncertainties
Requires-Dist: docopt
Requires-Dist: nestedtext
Requires-Dist: pydantic
Requires-Dist: byoc
Requires-Dist: tabulate
Requires-Dist: tidyexc
Requires-Dist: sphinx ; extra == "doc"
Requires-Dist: sphinx_rtd_theme ; extra == "doc"
Requires-Dist: autoclasstoc ; extra == "doc"
Requires-Dist: pytest ; extra == "test"
Requires-Dist: pytest-tmp-files ; extra == "test"
Requires-Dist: parametrize_from_file ; extra == "test"
Requires-Dist: re-assert ; extra == "test"
Requires-Dist: tqdm ; extra == "test"
Project-URL: Bug Tracker, https://github.com/kalekundert/cfu_count/issues
Project-URL: Continuous Integration, https://github.com/kalekundert/cfu_count/actions
Project-URL: Documentation, https://cfu_count.readthedocs.io/en/latest/
Project-URL: Test Coverage, https://coveralls.io/github/kalekundert/cfu_count
Project-URL: Version Control, https://github.com/kalekundert/cfu_count
Provides-Extra: doc
Provides-Extra: test
